LICENSE
MANIFEST.in
README.rst
setup.py
exclusiveprocess/__init__.py
exclusiveprocess.egg-info/PKG-INFO
exclusiveprocess.egg-info/SOURCES.txt
exclusiveprocess.egg-info/dependency_links.txt
exclusiveprocess.egg-info/top_level.txt