Metadata-Version: 1.1
Name: exclusiveprocess
Version: 0.9.4
Summary: Exclusive process locking to ensure that your code does not execute concurrently, using POSIX file locking.
Home-page: https://github.com/JoshData/exclusiveprocess
Author: Joshua Tauberer
Author-email: jt@occams.info
License: CC0 (copyright waived)
Keywords: exclusive process POSIX lock pid concurrent global system
Platform: UNKNOWN
Classifier: Development Status :: 5 - Production/Stable
Classifier: License :: CC0 1.0 Universal (CC0 1.0) Public Domain Dedication
Classifier: Intended Audience :: Developers
Classifier: Topic :: Software Development :: Libraries :: Python Modules
Classifier: Programming Language :: Python :: 3
Classifier: Programming Language :: Python :: 3.4
Classifier: Programming Language :: Python :: 3.5
Classifier: Programming Language :: Python :: 3.6
